lapidary_base/__init__.py
lapidary_base/_params.py
lapidary_base/absent.py
lapidary_base/api_base.py
lapidary_base/http_consts.py
lapidary_base/mime.py
lapidary_base/params.py
lapidary_base/pydantic_utils.py
lapidary_base/request.py
lapidary_base/response.py
lapidary_base/security.py
lapidary_base-0.5.1.dist-info/WHEEL
lapidary_base-0.5.1.dist-info/METADATA
lapidary_base-0.5.1.dist-info/RECORD
